langchain_elasticsearch/__init__.py
langchain_elasticsearch/_async/cache.py
langchain_elasticsearch/_async/chat_history.py
langchain_elasticsearch/_async/embeddings.py
langchain_elasticsearch/_async/retrievers.py
langchain_elasticsearch/_async/vectorstores.py
langchain_elasticsearch/_sync/cache.py
langchain_elasticsearch/_sync/chat_history.py
langchain_elasticsearch/_sync/embeddings.py
langchain_elasticsearch/_sync/retrievers.py
langchain_elasticsearch/_sync/vectorstores.py
langchain_elasticsearch/_utilities.py
langchain_elasticsearch/cache.py
langchain_elasticsearch/chat_history.py
langchain_elasticsearch/client.py
langchain_elasticsearch/embeddings.py
langchain_elasticsearch/py.typed
langchain_elasticsearch/retrievers.py
langchain_elasticsearch/vectorstores.py
langchain_elasticsearch_lc1-1.0.2.dist-info/METADATA
langchain_elasticsearch_lc1-1.0.2.dist-info/WHEEL
langchain_elasticsearch_lc1-1.0.2.dist-info/licenses/LICENSE
langchain_elasticsearch_lc1-1.0.2.dist-info/RECORD
