Metadata-Version: 2.4
Name: langchain-elasticsearch-lc1
Version: 1.0.2
Summary: An integration package connecting Elasticsearch and LangChain
License: MIT
License-File: LICENSE
Author: vekise-guo
Requires-Python: >=3.10,<4.0
Classifier: License :: OSI Approved :: MIT License
Classifier: Programming Language :: Python :: 3
Classifier: Programming Language :: Python :: 3.10
Classifier: Programming Language :: Python :: 3.11
Classifier: Programming Language :: Python :: 3.12
Classifier: Programming Language :: Python :: 3.13
Classifier: Programming Language :: Python :: 3.14
Requires-Dist: elasticsearch[vectorstore-mmr] (>=8.16.0,<=9.2.0)
Requires-Dist: langchain-core (>=1.1.1,<2.0.0)
Project-URL: Repository, https://github.com/vekise-guo/langchain-elastic
Project-URL: Source Code, https://github.com/vekise-guo/langchain-elastic/tree/main/libs/elasticsearch
